[{"model": "offers.hotel", "pk": 1, "fields": {"name": "Hotel garni Meledrio", "region": "Val di Sole, Włochy", "standard": 5, "location": "14 Via Campiglio, 38025 Dimaro, Włochy", "available_meals": ["BB", "HB"]}}, {"model": "offers.hotel", "pk": 2, "fields": {"name": "Hotel Campo de' Fiori", "region": "Rzym, Włochy", "standard": 5, "location": "Via del Biscione, 6, 00186 Rzym, Włochy", "available_meals": ["RO", "BB"]}}, {"model": "offers.hotel", "pk": 3, "fields": {"name": "Island City Hotel", "region": "Rodos, Grecja", "standard": 4, "location": "25is Martiou 1, Rodos 851 00, Greece", "available_meals": ["FB", "AI"]}}, {"model": "offers.hotel", "pk": 4, "fields": {"name": "Rosengarten Dolomiti Spa Hotel", "region": "Madonna di Campiglio", "standard": 5, "location": "Viale Dolomiti di Brenta, 71, 38086 Madonna di Campiglio TN, Italy", "available_meals": ["BB", "HB"]}}, {"model": "offers.hotel", "pk": 5, "fields": {"name": "Hotel Sagrada Familia Apartments", "region": "Barcelona, Hiszpania", "standard": 4, "location": "Sagrada Família, Barcelona, Catalonia, Spain", "available_meals": ["RO"]}}, {"model": "offers.hotel", "pk": 6, "fields": {"name": "B&B HOTEL Berlin-Alexanderplatz", "region": "Berlin, Niemcy", "standard": 3, "location": "Voltairestraße 3a, 10179 Berlin", "available_meals": ["RO", "BB"]}}, {"model": "offers.room", "pk": 1, "fields": {"hotel": 1, "name": "Pokój czteroosobowy deluxe", "max_occupancy": 4, "size_m2": 41, "beds_description": "1x double king size + 2x single", "has_kitchen": true, "has_balcony": true, "has_air_conditioning": true, "has_wifi": true, "view_type": "góry", "price_per_night": "1800.00"}}, {"model": "offers.room", "pk": 2, "fields": {"hotel": 1, "name": "Pokój czteroosobowy", "max_occupancy": 4, "size_m2": 31, "beds_description": "1x double, 2x single", "has_kitchen": false, "has_balcony": true, "has_air_conditioning": false, "has_wifi": true, "view_type": "miasto", "price_per_night": "830.00"}}, {"model": "offers.room", "pk": 3, "fields": {"hotel": 2, "name": "Pokój dwuosobowy deluxe", "max_occupancy": 2, "size_m2": 24, "beds_description": "King size bed", "has_kitchen": false, "has_balcony": true, "has_air_conditioning": false, "has_wifi": true, "view_type": "Miasto", "price_per_night": "599.00"}}, {"model": "offers.room", "pk": 4, "fields": {"hotel": 3, "name": "Apartament czteroosobowy", "max_occupancy": 4, "size_m2": 53, "beds_description": "1x double, 2x single", "has_kitchen": false, "has_balcony": true, "has_air_conditioning": true, "has_wifi": true, "view_type": "Plaża", "price_per_night": "630.00"}}, {"model": "offers.room", "pk": 5, "fields": {"hotel": 4, "name": "Górski pokój", "max_occupancy": 2, "size_m2": 35, "beds_description": "King size bed", "has_kitchen": true, "has_balcony": true, "has_air_conditioning": true, "has_wifi": true, "view_type": "Góry", "price_per_night": "930.00"}}, {"model": "offers.room", "pk": 6, "fields": {"hotel": 5, "name": "Mały apartament pięcioosobowy", "max_occupancy": 5, "size_m2": 32, "beds_description": "3x single, 1x double", "has_kitchen": false, "has_balcony": false, "has_air_conditioning": true, "has_wifi": true, "view_type": "Park", "price_per_night": "780.00"}}, {"model": "offers.room", "pk": 7, "fields": {"hotel": 6, "name": "Rodzinny pokój czteroosobowy", "max_occupancy": 4, "size_m2": 28, "beds_description": "1x double, 2x single", "has_kitchen": true, "has_balcony": false, "has_air_conditioning": false, "has_wifi": true, "view_type": "Miasto", "price_per_night": "560.00"}}, {"model": "offers.flight", "pk": 1, "fields": {"flight_number": "W6 1234", "carrier": "Alitalia", "departure_time": "2026-03-13T09:50:00Z", "arrival_time": "2026-03-13T12:40:00Z", "departure_airport": "WAW", "arrival_airport": "BZ", "region": "Bolzano (BZ), Trentino-Alto Adige, Italy", "price_per_person": "320.00"}}, {"model": "offers.flight", "pk": 2, "fields": {"flight_number": "W6 1235", "carrier": "Alitalia", "departure_time": "2026-03-21T12:30:00Z", "arrival_time": "2026-03-21T14:50:00Z", "departure_airport": "BZ", "arrival_airport": "WAW", "region": "Warsaw, Masovian Voivodeship, Poland", "price_per_person": "210.00"}}, {"model": "offers.flight", "pk": 3, "fields": {"flight_number": "W7 3456", "carrier": "Alitalia", "departure_time": "2026-03-13T03:20:00Z", "arrival_time": "2026-03-13T05:30:00Z", "departure_airport": "WAW", "arrival_airport": "BZ", "region": "Bolzano (BZ), Trentino-Alto Adige, Italy", "price_per_person": "110.00"}}, {"model": "offers.flight", "pk": 4, "fields": {"flight_number": "W4 1242", "carrier": "Lot", "departure_time": "2026-05-01T12:00:00Z", "arrival_time": "2026-05-01T14:10:00Z", "departure_airport": "WAW", "arrival_airport": "FCO", "region": "Warsaw, Masovian Voivodeship, Poland", "price_per_person": "450.00"}}, {"model": "offers.flight", "pk": 5, "fields": {"flight_number": "W8 3543", "carrier": "Lot", "departure_time": "2026-05-05T17:30:00Z", "arrival_time": "2026-05-05T20:20:00Z", "departure_airport": "FCO", "arrival_airport": "WAW", "region": "Rome, Lazio, Italy", "price_per_person": "580.00"}}, {"model": "offers.flight", "pk": 6, "fields": {"flight_number": "W3 2743", "carrier": "Ryanair", "departure_time": "2026-07-12T08:10:00Z", "arrival_time": "2026-07-12T11:50:00Z", "departure_airport": "RHO", "arrival_airport": "WRO", "region": "Rhodes, South Aegean, Greece", "price_per_person": "350.00"}}, {"model": "offers.flight", "pk": 7, "fields": {"flight_number": "W3 8946", "carrier": "Ryanair", "departure_time": "2026-07-19T12:20:00Z", "arrival_time": "2026-07-19T16:10:00Z", "departure_airport": "WRO", "arrival_airport": "RHO", "region": "Wrocław, Lower Silesian Voivodeship, Poland", "price_per_person": "220.00"}}, {"model": "offers.flight", "pk": 8, "fields": {"flight_number": "F3 2816", "carrier": "WizzAir", "departure_time": "2026-02-26T13:50:00Z", "arrival_time": "2026-02-26T14:40:00Z", "departure_airport": "LIDT", "arrival_airport": "POZ", "region": "Trento (TN), Trentino-Alto Adige, Italy", "price_per_person": "430.00"}}, {"model": "offers.flight", "pk": 9, "fields": {"flight_number": "F4 2835", "carrier": "WizzAir", "departure_time": "2026-02-19T12:10:00Z", "arrival_time": "2026-02-19T13:50:00Z", "departure_airport": "POZ", "arrival_airport": "LIDT", "region": "Poznań, Greater Poland Voivodeship, Poland", "price_per_person": "560.00"}}, {"model": "offers.flight", "pk": 10, "fields": {"flight_number": "F5 2846", "carrier": "WizzAir", "departure_time": "2026-04-01T07:30:00Z", "arrival_time": "2026-04-01T10:50:00Z", "departure_airport": "GDN", "arrival_airport": "BCN", "region": "Gdańsk, Pomeranian Voivodeship, Poland", "price_per_person": "380.00"}}, {"model": "offers.flight", "pk": 11, "fields": {"flight_number": "F9 2625", "carrier": "WizzAir", "departure_time": "2026-04-06T06:30:00Z", "arrival_time": "2026-04-06T09:40:00Z", "departure_airport": "BCN", "arrival_airport": "GDN", "region": "Barcelona, Catalonia, Spain", "price_per_person": "435.00"}}, {"model": "offers.flight", "pk": 12, "fields": {"flight_number": "W5 2638", "carrier": "Lot", "departure_time": "2026-03-26T05:30:00Z", "arrival_time": "2026-03-26T06:20:00Z", "departure_airport": "WAW", "arrival_airport": "BER", "region": "Warsaw, Masovian Voivodeship, Poland", "price_per_person": "340.00"}}, {"model": "offers.flight", "pk": 13, "fields": {"flight_number": "W5 2059", "carrier": "Lot", "departure_time": "2026-03-28T18:30:00Z", "arrival_time": "2026-03-28T19:45:00Z", "departure_airport": "BER", "arrival_airport": "WAW", "region": "Berlin, Brandenburg, Germany", "price_per_person": "230.00"}}, {"model": "offers.offer", "pk": 1, "fields": {"title": "Narty w Val di Sole", "region": "Val di Sole", "start_date": "2026-03-13", "end_date": "2026-03-21", "base_price": "4920.00", "available_seats": 4, "description": "Wyjazd narciarski do malowniczej doliny Val di Sole we Włoszech, jednego z najpopularniejszych regionów narciarskich w Alpach. Oferta obejmuje komfortowy pobyt w górskim kurorcie z dostępem do rozbudowanej infrastruktury narciarskiej, liczne trasy o zróżnicowanym poziomie trudności oraz nowoczesne wyciągi.\r\n\r\nRegion Val di Sole słynie z doskonałych warunków śniegowych, pięknych widoków oraz bogatej oferty après-ski. Wyjazd idealny zarówno dla osób początkujących, jak i zaawansowanych narciarzy.\r\n\r\nW cenie uwzględniono zakwaterowanie, skipass oraz możliwość skorzystania z dodatkowych atrakcji regionu.", "image": "offers/ski_NmUPgzO.jpg", "is_active": true, "promoted": true, "created_at": "2026-01-02T15:50:12.410Z", "hotel": 1, "room": 2, "outbound_flight": 1, "return_flight": 2, "meal_plan": "BB"}}, {"model": "offers.offer", "pk": 2, "fields": {"title": "bleh", "region": "a", "start_date": "2026-01-13", "end_date": "2026-01-20", "base_price": "13.00", "available_seats": 2, "description": "wsedrfgh", "image": "offers/island_ylhzP0V.jpg", "is_active": false, "promoted": false, "created_at": "2026-01-06T10:22:49.170Z", "hotel": 1, "room": 2, "outbound_flight": 1, "return_flight": 2, "meal_plan": "HB"}}, {"model": "offers.offer", "pk": 3, "fields": {"title": "Przedłużony weekend w Rzymie", "region": "Rzym, Włochy", "start_date": "2026-05-01", "end_date": "2026-05-05", "base_price": "4350.00", "available_seats": 2, "description": "Krótki city break do Rzymu obejmujący przelot oraz zakwaterowanie w hotelu położonym w pobliżu centrum miasta. Oferta przeznaczona dla osób planujących intensywne zwiedzanie w trakcie kilku dni pobytu.\r\nW czasie wyjazdu możliwe jest zobaczenie najważniejszych zabytków miasta, takich jak Koloseum, Forum Romanum czy Watykan.", "image": "offers/pexels-chaitaastic-1797161.jpg", "is_active": true, "promoted": false, "created_at": "2026-01-14T01:50:28.543Z", "hotel": 2, "room": 3, "outbound_flight": 4, "return_flight": 5, "meal_plan": "RO"}}, {"model": "offers.offer", "pk": 4, "fields": {"title": "Rodzinne wakacje na Rodos", "region": "Rodos, Grecja", "start_date": "2026-07-12", "end_date": "2026-07-19", "base_price": "2150.00", "available_seats": 4, "description": "Tygodniowy wypoczynek na wyspie Rodos w hotelu przystosowanym do pobytu rodzin z dziećmi. Oferta obejmuje przelot, zakwaterowanie oraz wyżywienie w formule All Inclusive.\r\n\r\nHotel położony jest w pobliżu plaży i oferuje podstawowe udogodnienia rekreacyjne. Wyjazd przeznaczony dla rodzin szukających spokojnego wypoczynku w sezonie letnim.", "image": "offers/68f273eb310fc.jpg", "is_active": true, "promoted": true, "created_at": "2026-01-14T02:14:46.154Z", "hotel": 3, "room": 4, "outbound_flight": 7, "return_flight": 6, "meal_plan": "AI"}}, {"model": "offers.offer", "pk": 5, "fields": {"title": "Narty w Madonnie dla dwojga", "region": "Madonna di Campiglio, Włochy", "start_date": "2026-02-19", "end_date": "2026-02-26", "base_price": "3900.00", "available_seats": 2, "description": "Wyjazd narciarski do popularnego kurortu Madonna di Campiglio, położonego w masywie Brenta Dolomiti. Region oferuje rozbudowaną sieć nowoczesnych tras narciarskich o zróżnicowanym poziomie trudności oraz doskonałe warunki śniegowe przez cały sezon zimowy.\r\n\r\nOferta obejmuje zakwaterowanie w hotelu w pobliżu stoków, przelot oraz możliwość korzystania z lokalnej infrastruktury narciarskiej.", "image": "offers/madonna-di-campiglio.60de2784.jpg", "is_active": true, "promoted": true, "created_at": "2026-01-14T02:30:50.660Z", "hotel": 4, "room": 5, "outbound_flight": 9, "return_flight": 8, "meal_plan": "BB"}}, {"model": "offers.offer", "pk": 6, "fields": {"title": "City break w Barcelonie", "region": "Barcelona, Hiszpania", "start_date": "2026-04-01", "end_date": "2026-04-06", "base_price": "3200.00", "available_seats": 5, "description": "Krótki wyjazd typu city break dla przyjaciół do Barcelony – miasta łączącego bogatą historię, architekturę i śródziemnomorski klimat. W trakcie pobytu możliwe jest zwiedzanie najważniejszych atrakcji, a także odpoczynek na miejskich plażach.\r\n\r\nOferta obejmuje zakwaterowanie w hotelu położonym w dogodnej lokalizacji, przelot oraz czas wolny na samodzielne zwiedzanie miasta. Wyjazd idealny na przedłużony weekend.", "image": "offers/barcelona-01-753x500.jpg", "is_active": true, "promoted": false, "created_at": "2026-01-14T02:38:39.384Z", "hotel": 5, "room": 6, "outbound_flight": 10, "return_flight": 11, "meal_plan": "RO"}}, {"model": "offers.offer", "pk": 7, "fields": {"title": "Rodzinny city break w Berlinie", "region": "Berlin, Niemcy", "start_date": "2026-03-26", "end_date": "2026-03-28", "base_price": "1780.00", "available_seats": 4, "description": "Krótki wyjazd typu city break do Berlina, jednego z najważniejszych ośrodków kulturalnych i historycznych Europy. Program wyjazdu umożliwia zwiedzanie takich miejsc jak Brama Brandenburska, Reichstag, Wyspa Muzeów czy pozostałości Muru Berlińskiego.\r\n\r\nOferta skierowana jest dla rodzin poszukujących niedrogiego wyjazdu weekendowego, łączącego zwiedzanie miasta z możliwością samodzielnego planowania czasu wolnego. W cenie uwzględniono przelot oraz noclegi w hotelu o standardzie turystycznym.", "image": "offers/64e46db516a42ac570e30ed9_img-blogpost-berlin-besuch.jpg", "is_active": true, "promoted": true, "created_at": "2026-01-14T02:46:53.493Z", "hotel": 6, "room": 7, "outbound_flight": 12, "return_flight": 13, "meal_plan": "BB"}}]
